README.md
setup.py
pyslo/__init__.py
pyslo/conftest.py
pyslo/sli.py
pyslo.egg-info/PKG-INFO
pyslo.egg-info/SOURCES.txt
pyslo.egg-info/dependency_links.txt
pyslo.egg-info/requires.txt
pyslo.egg-info/top_level.txt
pyslo/metric_client/__init__.py
pyslo/metric_client/metric_client.py
pyslo/metric_client/stackdriver/__init__.py
pyslo/metric_client/stackdriver/stackdriver_filter.py
pyslo/metric_client/stackdriver/stackdriver_metric_client.py